freezeblaster/__init__.py
freezeblaster/py.typed
freezeblaster-0.6.0.dist-info/WHEEL
freezeblaster-0.6.0.dist-info/METADATA
freezeblaster-0.6.0.dist-info/RECORD
