Metadata-Version: 2.3
Name: freezeblaster
Version: 0.6.0
Summary: FreezeBlaster is a library that allows time travel by mocking the datetime module
Author: Jakub Jantosik
Author-email: Jakub Jantosik <jakub.jantosik@gmail.com>
Classifier: Programming Language :: Python
Classifier: Programming Language :: Python :: 3
Classifier: Programming Language :: Python :: 3 :: Only
Classifier: Programming Language :: Python :: 3.10
Classifier: Programming Language :: Python :: 3.11
Classifier: Programming Language :: Python :: 3.12
Classifier: Programming Language :: Python :: 3.13
Classifier: Programming Language :: Python :: 3.14
Classifier: Intended Audience :: Developers
Classifier: Intended Audience :: Information Technology
Classifier: Operating System :: OS Independent
Classifier: Topic :: Software Development :: Libraries :: Python Modules
Requires-Dist: packaging>=24.0
Requires-Dist: python-dateutil>=2.7
Requires-Dist: types-python-dateutil>=2.7
Requires-Python: >=3.10
